Metadata-Version: 1.0
Name: inheritance-py-sa
Version: 0.1.0
Summary: Basic inheritance example
Home-page: UNKNOWN
Author: Saphal Adhikari
Author-email: franticarsenal@gmail.com
License: UNKNOWN
Platform: UNKNOWN
